docs/README.md
docs/api.md
docs/configuration.md
docs/examples.md
docs/index.md
docs/installation.md
docs/quickstart.md
fayda_py_sdk/__init__.py
fayda_py_sdk/client/__init__.py
fayda_py_sdk/client/ekyc_client.py
fayda_py_sdk/client/ekyc_client_config.py
fayda_py_sdk/config/__init__.py
fayda_py_sdk/config/config_builder.py
fayda_py_sdk/constants/__init__.py
fayda_py_sdk/constants/auth_constants.py
fayda_py_sdk/dto/__init__.py
fayda_py_sdk/dto/request/__init__.py
fayda_py_sdk/dto/request/auth_request_dto.py
fayda_py_sdk/dto/request/auth_type_dto.py
fayda_py_sdk/dto/request/base_auth_request_dto.py
fayda_py_sdk/dto/request/bio_identity_info_dto.py
fayda_py_sdk/dto/request/encryption_request_dto.py
fayda_py_sdk/dto/request/otp_request_dto.py
fayda_py_sdk/dto/request/request_dto.py
fayda_py_sdk/dto/response/__init__.py
fayda_py_sdk/dto/response/encryption_response_dto.py
fayda_py_sdk/helper/__init__.py
fayda_py_sdk/helper/crypto_core.py
fayda_py_sdk/helper/crypto_util.py
fayda_py_sdk/helper/crypto_utility.py
fayda_py_sdk/helper/hmac_util.py
fayda_py_sdk/service/__init__.py
fayda_py_sdk/service/auth_service.py
fayda_py_sdk/service/ekyc_service.py
fayda_py_sdk/service/otp_service.py
fayda_py_sdk/util/__init__.py
fayda_py_sdk/util/key_mgr_util.py
fayda_py_sdk/util/signature_util.py
fayda_python_sdk-1.0.3.dist-info/licenses/LICENSE
fayda_python_sdk-1.0.3.dist-info/METADATA
fayda_python_sdk-1.0.3.dist-info/WHEEL
fayda_python_sdk-1.0.3.dist-info/top_level.txt
fayda_python_sdk-1.0.3.dist-info/RECORD
