Metadata-Version: 2.4
Name: fayda-python-sdk
Version: 1.0.3
Summary: Python SDK for Fayda IDA (Identity Authentication) - OTP, Authentication and eKYC services
Author-email: Fayda Team <api_support@fayda.et>, Cherinet Hailu <cherinet@id.et>, Amanuel Gulti <amanuelgulti@id.et>
Maintainer-email: Fayda Team <api_support@fayda.et>
License-Expression: MIT
Project-URL: Homepage, https://github.com/National-ID-Program-Ethiopia/python-ida-sdk
Project-URL: Documentation, https://national-id-program-ethiopia.github.io/python-ida-sdk
Project-URL: Repository, https://github.com/National-ID-Program-Ethiopia/python-ida-sdk
Project-URL: Issues, https://github.com/National-ID-Program-Ethiopia/python-ida-sdk/issues
Keywords: fayda,ida,authentication,ekyc,otp,sdk,identity
Classifier: Development Status :: 4 - Beta
Classifier: Intended Audience :: Developers
Classifier: Programming Language :: Python :: 3
Classifier: Programming Language :: Python :: 3.8
Classifier: Programming Language :: Python :: 3.9
Classifier: Programming Language :: Python :: 3.10
Classifier: Programming Language :: Python :: 3.11
Classifier: Topic :: Software Development :: Libraries :: Python Modules
Classifier: Topic :: Security
Requires-Python: >=3.8
License-File: LICENSE
Requires-Dist: cryptography>=41.0.0
Requires-Dist: pyjwt>=2.8.0
Requires-Dist: requests>=2.31.0
Provides-Extra: dev
Requires-Dist: pytest>=7.0.0; extra == "dev"
Requires-Dist: pytest-cov>=4.0.0; extra == "dev"
Requires-Dist: black>=23.0.0; extra == "dev"
Requires-Dist: flake8>=6.0.0; extra == "dev"
Requires-Dist: mypy>=1.0.0; extra == "dev"
Dynamic: license-file
